pwn-stubs/__init__.pyi
pwnlib-stubs/__init__.pyi
pwnlib-stubs/asm.pyi
pwnlib-stubs/context.pyi
pwnlib-stubs/elf/__init__.pyi
pwnlib-stubs/fiddling.pyi
pwnlib-stubs/fmtstr.pyi
pwnlib-stubs/gdb.pyi
pwnlib-stubs/log.pyi
pwnlib-stubs/shellcraft.pyi
pwnlib-stubs/tubes/__init__.pyi
pwnlib-stubs/tubes/listen.pyi
pwnlib-stubs/tubes/process.pyi
pwnlib-stubs/tubes/remote.pyi
pwnlib-stubs/tubes/ssh.pyi
pwnlib-stubs/tubes/tube.pyi
pwnlib-stubs/util/__init__.pyi
pwnlib-stubs/util/cyclic.pyi
pwnlib-stubs/util/packing.pyi
pwntools_stubs-0.1.2.dist-info/METADATA
pwntools_stubs-0.1.2.dist-info/WHEEL
pwntools_stubs-0.1.2.dist-info/RECORD
