Metadata-Version: 2.1
Name: pwntools-stubs
Version: 0.1.2
Summary: Incomplete, and probably incorrect, stubs for pwntools
Author: rikyiso01
Author-email: riky.isola@gmail.com
Requires-Python: >=3.7,<4.0
Classifier: Programming Language :: Python :: 3
Classifier: Programming Language :: Python :: 3.7
Classifier: Programming Language :: Python :: 3.8
Classifier: Programming Language :: Python :: 3.9
Classifier: Programming Language :: Python :: 3.10
Classifier: Programming Language :: Python :: 3.11
Requires-Dist: pwntools (>=4.9.0,<5.0.0)
